{
  "entries": {
    "VRT": {
      "sleeve": "momentum",
      "opened_at": "2026-04-28T15:41:43.678948+00:00",
      "ref_price": 322.43,
      "qty": 30
    },
    "GEV": {
      "sleeve": "momentum",
      "opened_at": "2026-04-28T15:41:44.147867+00:00",
      "ref_price": 1120.23,
      "qty": 8
    },
    "AGX": {
      "sleeve": "momentum",
      "opened_at": "2026-04-28T15:41:45.110394+00:00",
      "ref_price": 601.83,
      "qty": 16
    },
    "FIX": {
      "sleeve": "swing",
      "opened_at": "2026-04-28T15:41:46.055083+00:00",
      "ref_price": 1794.04,
      "qty": 2
    },
    "AMRX": {
      "sleeve": "swing",
      "opened_at": "2026-04-28T15:41:48.681410+00:00",
      "ref_price": 13.09,
      "qty": 374
    },
    "AHR": {
      "sleeve": "swing",
      "opened_at": "2026-04-28T15:41:49.448406+00:00",
      "ref_price": 50.58,
      "qty": 96
    },
    "HWM": {
      "sleeve": "swing",
      "opened_at": "2026-04-28T15:41:51.044689+00:00",
      "ref_price": 241.7,
      "qty": 20
    },
    "GLW": {
      "sleeve": "swing",
      "opened_at": "2026-04-28T15:41:52.670716+00:00",
      "ref_price": 168.01,
      "qty": 29
    },
    "TSM": {
      "sleeve": "swing",
      "opened_at": "2026-04-30T13:30:39.656312+00:00",
      "ref_price": 393.83,
      "qty": 12
    },
    "CVNA": {
      "sleeve": "momentum",
      "opened_at": "2026-04-29T13:31:00.802699+00:00",
      "ref_price": 406.42,
      "qty": 24
    },
    "WDC": {
      "sleeve": "momentum",
      "opened_at": "2026-04-30T13:30:37.561619+00:00",
      "ref_price": 412.76,
      "qty": 24
    },
    "STX": {
      "sleeve": "swing",
      "opened_at": "2026-04-30T13:30:39.288053+00:00",
      "ref_price": 643.3,
      "qty": 7
    },
    "CIEN": {
      "sleeve": "swing",
      "opened_at": "2026-04-29T14:31:03.601598+00:00",
      "ref_price": 473.69,
      "qty": 10
    },
    "KLAC": {
      "sleeve": "swing",
      "opened_at": "2026-04-30T13:30:39.457798+00:00",
      "ref_price": 1816.21,
      "qty": 2
    },
    "APH": {
      "sleeve": "swing",
      "opened_at": "2026-04-30T13:30:49.783578+00:00",
      "ref_price": 148.38,
      "qty": 33
    },
    "DY": {
      "sleeve": "daytrade",
      "opened_at": "2026-04-30T13:30:50.066688+00:00",
      "ref_price": 409.32,
      "qty": 8
    },
    "PWR": {
      "sleeve": "daytrade",
      "opened_at": "2026-04-30T13:30:51.412595+00:00",
      "ref_price": 628.6,
      "qty": 5
    },
    "CAH": {
      "sleeve": "daytrade",
      "opened_at": "2026-04-30T13:30:51.770136+00:00",
      "ref_price": 202.82,
      "qty": 16
    },
    "PH": {
      "sleeve": "daytrade",
      "opened_at": "2026-04-30T13:30:52.206375+00:00",
      "ref_price": 947.5,
      "qty": 3
    }
  },
  "traded_today": {
    "2026-04-30": [
      "DY",
      "PWR",
      "CAH",
      "PH"
    ]
  },
  "breaker_fired_date": "2026-04-28",
  "scalper": {
    "positions": {
      "AAPL": {
        "symbol": "AAPL",
        "qty": 1,
        "entry_price": 271.63,
        "opened_at": "2026-04-30T14:05:33.469860+00:00",
        "signal": "orb",
        "stop": 269.73,
        "target": 274.35
      },
      "C": {
        "symbol": "C",
        "qty": 3,
        "entry_price": 128.155,
        "opened_at": "2026-04-30T14:10:37.671870+00:00",
        "signal": "relvol",
        "stop": 127.26,
        "target": 129.44
      },
      "BLK": {
        "symbol": "BLK",
        "qty": 1,
        "entry_price": 1050.385,
        "opened_at": "2026-04-30T14:10:37.716931+00:00",
        "signal": "orb",
        "stop": 1043.03,
        "target": 1060.89
      },
      "COST": {
        "symbol": "COST",
        "qty": 1,
        "entry_price": 1014.12,
        "opened_at": "2026-04-30T14:10:37.762472+00:00",
        "signal": "orb",
        "stop": 1007.02,
        "target": 1024.26
      },
      "HD": {
        "symbol": "HD",
        "qty": 1,
        "entry_price": 326.47,
        "opened_at": "2026-04-30T14:10:37.807083+00:00",
        "signal": "relvol",
        "stop": 324.18,
        "target": 329.73
      },
      "GS": {
        "symbol": "GS",
        "qty": 1,
        "entry_price": 916.33,
        "opened_at": "2026-04-30T14:20:55.269400+00:00",
        "signal": "orb",
        "stop": 909.92,
        "target": 925.49
      },
      "MS": {
        "symbol": "MS",
        "qty": 2,
        "entry_price": 188.11,
        "opened_at": "2026-04-30T14:20:55.330258+00:00",
        "signal": "orb",
        "stop": 186.79,
        "target": 189.99
      }
    },
    "fired_today": [
      {
        "symbol": "AAPL",
        "signal": "orb",
        "ts": "2026-04-30T14:05:33.469871+00:00"
      },
      {
        "symbol": "C",
        "signal": "relvol",
        "ts": "2026-04-30T14:10:37.671881+00:00"
      },
      {
        "symbol": "BLK",
        "signal": "orb",
        "ts": "2026-04-30T14:10:37.716941+00:00"
      },
      {
        "symbol": "COST",
        "signal": "orb",
        "ts": "2026-04-30T14:10:37.762484+00:00"
      },
      {
        "symbol": "HD",
        "signal": "relvol",
        "ts": "2026-04-30T14:10:37.807097+00:00"
      },
      {
        "symbol": "GS",
        "signal": "orb",
        "ts": "2026-04-30T14:20:55.269408+00:00"
      },
      {
        "symbol": "MS",
        "signal": "orb",
        "ts": "2026-04-30T14:20:55.330265+00:00"
      }
    ],
    "last_scan": null,
    "last_scan_date": "2026-04-30"
  }
}